{"success":true,"data":[{"timestamp":"1649937600","name":"3dudescapital","profit":"206196660869","dailyChange":-1084893,"weeklyChange":-45619743,"side":"Long"},{"timestamp":"1649937600","name":"Ak Shi Pian Zi","profit":"343973048259","dailyChange":0,"weeklyChange":0,"side":"-"},{"timestamp":"1649937600","name":"Amber Group","profit":"107837115830","dailyChange":-65533789,"weeklyChange":-309637716,"side":"Long"},{"timestamp":"1649937600","name":"Atom-Paint-Lizard","profit":"118182060196","dailyChange":-124686263,"weeklyChange":-389744198,"side":"Long"},{"timestamp":"1649937600","name":"Bog-Pear-Weasel","profit":"308759159231","dailyChange":-92177162,"weeklyChange":536158062,"side":"Long"},{"timestamp":"1649937600","name":"Chocolate-Flint-Falcon","profit":"148363230756","dailyChange":0,"weeklyChange":0,"side":"-"},{"timestamp":"1649937600","name":"Crypto Research","profit":"176454784734","dailyChange":0,"weeklyChange":0,"side":"-"},{"timestamp":"1649937600","name":"Disco-Solar-Fang","profit":"178656096085","dailyChange":925742,"weeklyChange":38927445,"side":"Short"},{"timestamp":"1649937600","name":"Fern-Ebony-Slave","profit":"132547494767","dailyChange":0,"weeklyChange":0,"side":"-"},{"timestamp":"1649937600","name":"Honeysuckle-South-Rib","profit":"197802789481","dailyChange":0,"weeklyChange":0,"side":"-"},{"timestamp":"1649937600","name":"Linen","profit":"125918509994","dailyChange":0,"weeklyChange":0,"side":"-"},{"timestamp":"1649937600","name":"Mercury-Wood-Sprite","profit":"847208332993","dailyChange":0,"weeklyChange":0,"side":"-"},{"timestamp":"1649937600","name":"Paper-Feather-Stallion","profit":"405461699789","dailyChange":0,"weeklyChange":0,"side":"-"},{"timestamp":"1649937600","name":"Prairie-Ballistic-Palm","profit":"119888270546","dailyChange":0,"weeklyChange":-142227243,"side":"-"},{"timestamp":"1649937600","name":"Prong-Buttercup-Whale","profit":"110542245449","dailyChange":0,"weeklyChange":0,"side":"-"},{"timestamp":"1649937600","name":"Quill-Rift-Hoof","profit":"176900995430","dailyChange":0,"weeklyChange":0,"side":"-"},{"timestamp":"1649937600","name":"Ripple-Great-Koala","profit":"147267677859","dailyChange":-27364467,"weeklyChange":530117916,"side":"Long"},{"timestamp":"1649937600","name":"Shubhodeep Das","profit":"197561007709","dailyChange":0,"weeklyChange":0,"side":"-"},{"timestamp":"1649937600","name":"Skitter-Peridot-Raven","profit":"165801269805","dailyChange":0,"weeklyChange":0,"side":"-"},{"timestamp":"1649937600","name":"SuDoResearch","profit":"127477304991","dailyChange":0,"weeklyChange":0,"side":"-"},{"timestamp":"1649937600","name":"Winter-Pink-Fang","profit":"112195310098","dailyChange":15426965,"weeklyChange":58363379,"side":"Short"},{"timestamp":"1649937600","name":"alamedaresearchltd@gmail.com","profit":"169670395643","dailyChange":0,"weeklyChange":0,"side":"-"},{"timestamp":"1649937600","name":"aoa","profit":"340011021011","dailyChange":1527052450,"weeklyChange":662364279,"side":"Short"},{"timestamp":"1649937600","name":"ningxin","profit":"241654552971","dailyChange":0,"weeklyChange":0,"side":"-"},{"timestamp":"1649937600","name":"xorq","profit":"127811730513","dailyChange":0,"weeklyChange":0,"side":"-"}]}