{"success":true,"data":[{"timestamp":"1649649600","name":"3dudescapital","profit":"206201204040","dailyChange":6600610,"weeklyChange":-94722027,"side":"Short"},{"timestamp":"1649649600","name":"Ak Shi Pian Zi","profit":"343973048259","dailyChange":0,"weeklyChange":0,"side":"-"},{"timestamp":"1649649600","name":"Amber Group","profit":"108061808309","dailyChange":-2381631,"weeklyChange":-115419864,"side":"Long"},{"timestamp":"1649649600","name":"Atom-Paint-Lizard","profit":"118493073687","dailyChange":-23153894,"weeklyChange":-17495168,"side":"Long"},{"timestamp":"1649649600","name":"Bog-Pear-Weasel","profit":"308597391348","dailyChange":-9436993,"weeklyChange":571768724,"side":"Long"},{"timestamp":"1649649600","name":"Chocolate-Flint-Falcon","profit":"148363230756","dailyChange":0,"weeklyChange":0,"side":"-"},{"timestamp":"1649649600","name":"Crypto Research","profit":"176454784734","dailyChange":0,"weeklyChange":0,"side":"-"},{"timestamp":"1649649600","name":"Disco-Solar-Fang","profit":"178652219386","dailyChange":-5632318,"weeklyChange":80826555,"side":"Long"},{"timestamp":"1649649600","name":"Fern-Ebony-Slave","profit":"132547494767","dailyChange":0,"weeklyChange":0,"side":"-"},{"timestamp":"1649649600","name":"Honeysuckle-South-Rib","profit":"197802789481","dailyChange":0,"weeklyChange":0,"side":"-"},{"timestamp":"1649649600","name":"Linen","profit":"125918509994","dailyChange":0,"weeklyChange":0,"side":"-"},{"timestamp":"1649649600","name":"Mercury-Wood-Sprite","profit":"847208332993","dailyChange":0,"weeklyChange":0,"side":"-"},{"timestamp":"1649649600","name":"Paper-Feather-Stallion","profit":"405461699789","dailyChange":0,"weeklyChange":0,"side":"-"},{"timestamp":"1649649600","name":"Prairie-Ballistic-Palm","profit":"119888270546","dailyChange":0,"weeklyChange":-113547093,"side":"-"},{"timestamp":"1649649600","name":"Prong-Buttercup-Whale","profit":"110542245449","dailyChange":0,"weeklyChange":0,"side":"-"},{"timestamp":"1649649600","name":"Quill-Rift-Hoof","profit":"176900995430","dailyChange":0,"weeklyChange":0,"side":"-"},{"timestamp":"1649649600","name":"Ripple-Great-Koala","profit":"147455103346","dailyChange":122298018,"weeklyChange":507272594,"side":"Short"},{"timestamp":"1649649600","name":"Shubhodeep Das","profit":"197561007709","dailyChange":0,"weeklyChange":0,"side":"-"},{"timestamp":"1649649600","name":"Skitter-Peridot-Raven","profit":"165801269805","dailyChange":0,"weeklyChange":0,"side":"-"},{"timestamp":"1649649600","name":"SuDoResearch","profit":"127477304991","dailyChange":0,"weeklyChange":0,"side":"-"},{"timestamp":"1649649600","name":"Winter-Pink-Fang","profit":"112170893324","dailyChange":3057150,"weeklyChange":59241436,"side":"Short"},{"timestamp":"1649649600","name":"alamedaresearchltd@gmail.com","profit":"169670395643","dailyChange":0,"weeklyChange":0,"side":"-"},{"timestamp":"1649649600","name":"aoa","profit":"338286390554","dailyChange":72,"weeklyChange":-2241013848,"side":"Short"},{"timestamp":"1649649600","name":"ningxin","profit":"241654552971","dailyChange":0,"weeklyChange":0,"side":"-"},{"timestamp":"1649649600","name":"xorq","profit":"127811730513","dailyChange":0,"weeklyChange":0,"side":"-"}]}