{"success":true,"data":[{"timestamp":"1666897200","name":"3dudescapital","profit":"265074459488","dailyChange":0,"weeklyChange":3777552147,"side":"-"},{"timestamp":"1666897200","name":"Amber Group","profit":"101959601080","dailyChange":63407,"weeklyChange":-24296450,"side":"Short"},{"timestamp":"1666897200","name":"Atom-Paint-Lizard","profit":"127781272294","dailyChange":68680775,"weeklyChange":495150398,"side":"Short"},{"timestamp":"1666897200","name":"Bog-Pear-Weasel","profit":"313493428132","dailyChange":58375096,"weeklyChange":-35985073,"side":"Short"},{"timestamp":"1666897200","name":"Bramble-Dark-Grasp","profit":"193061095868","dailyChange":1640180000,"weeklyChange":2200084722,"side":"Long"},{"timestamp":"1666897200","name":"Chatter-Paper-Snout","profit":"346599050000","dailyChange":2410000,"weeklyChange":601310000,"side":"Short"},{"timestamp":"1666897200","name":"Chocolate-Flint-Falcon","profit":"148363230756","dailyChange":0,"weeklyChange":0,"side":"-"},{"timestamp":"1666897200","name":"Crypto Research","profit":"176454784734","dailyChange":0,"weeklyChange":0,"side":"-"},{"timestamp":"1666897200","name":"Disco-Solar-Fang","profit":"241458065161","dailyChange":4131596,"weeklyChange":27842916,"side":"Short"},{"timestamp":"1666897200","name":"Fern-Ebony-Slave","profit":"132547494767","dailyChange":0,"weeklyChange":0,"side":"-"},{"timestamp":"1666897200","name":"Honeysuckle-South-Rib","profit":"197802789481","dailyChange":0,"weeklyChange":0,"side":"-"},{"timestamp":"1666897200","name":"Linen","profit":"123590404550","dailyChange":0,"weeklyChange":0,"side":"-"},{"timestamp":"1666897200","name":"Mercury-Wood-Sprite","profit":"847208332993","dailyChange":0,"weeklyChange":0,"side":"-"},{"timestamp":"1666897200","name":"Paper-Feather-Stallion","profit":"405461699789","dailyChange":0,"weeklyChange":0,"side":"-"},{"timestamp":"1666897200","name":"Prong-Buttercup-Whale","profit":"110542245449","dailyChange":0,"weeklyChange":0,"side":"-"},{"timestamp":"1666897200","name":"Quill-Rift-Hoof","profit":"176900995430","dailyChange":0,"weeklyChange":0,"side":"-"},{"timestamp":"1666897200","name":"Ripple-Great-Koala","profit":"138575595642","dailyChange":-506295569,"weeklyChange":-594522758,"side":"Long"},{"timestamp":"1666897200","name":"Shubhodeep Das","profit":"197561007709","dailyChange":0,"weeklyChange":0,"side":"-"},{"timestamp":"1666897200","name":"Skitter-Peridot-Raven","profit":"165801269805","dailyChange":0,"weeklyChange":0,"side":"-"},{"timestamp":"1666897200","name":"SuDoResearch","profit":"127477304991","dailyChange":0,"weeklyChange":0,"side":"-"},{"timestamp":"1666897200","name":"Winter-Pink-Fang","profit":"109861797880","dailyChange":6034177,"weeklyChange":40664446,"side":"Short"},{"timestamp":"1666897200","name":"alamedaresearchltd@gmail.com","profit":"169670395643","dailyChange":0,"weeklyChange":0,"side":"-"},{"timestamp":"1666897200","name":"aoa","profit":"366993681522","dailyChange":5222313694,"weeklyChange":5153977235,"side":"Short"},{"timestamp":"1666897200","name":"fhrp","profit":"331620529937","dailyChange":0,"weeklyChange":0,"side":"-"},{"timestamp":"1666897200","name":"xorq","profit":"127811730513","dailyChange":0,"weeklyChange":0,"side":"-"}]}