{"success":true,"data":[{"timestamp":"1649908800","name":"3dudescapital","profit":"206206323952","dailyChange":8578190,"weeklyChange":-35956660,"side":"Long"},{"timestamp":"1649908800","name":"Ak Shi Pian Zi","profit":"343973048259","dailyChange":0,"weeklyChange":0,"side":"-"},{"timestamp":"1649908800","name":"Amber Group","profit":"107839194995","dailyChange":-63454624,"weeklyChange":-307558551,"side":"Short"},{"timestamp":"1649908800","name":"Atom-Paint-Lizard","profit":"118242004486","dailyChange":-64741973,"weeklyChange":-329799908,"side":"Short"},{"timestamp":"1649908800","name":"Bog-Pear-Weasel","profit":"308845483918","dailyChange":-5852475,"weeklyChange":622482749,"side":"Short"},{"timestamp":"1649908800","name":"Chocolate-Flint-Falcon","profit":"148363230756","dailyChange":0,"weeklyChange":0,"side":"-"},{"timestamp":"1649908800","name":"Crypto Research","profit":"176454784734","dailyChange":0,"weeklyChange":0,"side":"-"},{"timestamp":"1649908800","name":"Disco-Solar-Fang","profit":"178647850551","dailyChange":-7319792,"weeklyChange":30681911,"side":"Short"},{"timestamp":"1649908800","name":"Fern-Ebony-Slave","profit":"132547494767","dailyChange":0,"weeklyChange":0,"side":"-"},{"timestamp":"1649908800","name":"Honeysuckle-South-Rib","profit":"197802789481","dailyChange":0,"weeklyChange":0,"side":"-"},{"timestamp":"1649908800","name":"Linen","profit":"125918509994","dailyChange":0,"weeklyChange":0,"side":"-"},{"timestamp":"1649908800","name":"Mercury-Wood-Sprite","profit":"847208332993","dailyChange":0,"weeklyChange":0,"side":"-"},{"timestamp":"1649908800","name":"Paper-Feather-Stallion","profit":"405461699789","dailyChange":0,"weeklyChange":0,"side":"-"},{"timestamp":"1649908800","name":"Prairie-Ballistic-Palm","profit":"119888270546","dailyChange":0,"weeklyChange":-142227243,"side":"-"},{"timestamp":"1649908800","name":"Prong-Buttercup-Whale","profit":"110542245449","dailyChange":0,"weeklyChange":0,"side":"-"},{"timestamp":"1649908800","name":"Quill-Rift-Hoof","profit":"176900995430","dailyChange":0,"weeklyChange":0,"side":"-"},{"timestamp":"1649908800","name":"Ripple-Great-Koala","profit":"147297689371","dailyChange":2647045,"weeklyChange":560129428,"side":"Long"},{"timestamp":"1649908800","name":"Shubhodeep Das","profit":"197561007709","dailyChange":0,"weeklyChange":0,"side":"-"},{"timestamp":"1649908800","name":"Skitter-Peridot-Raven","profit":"165801269805","dailyChange":0,"weeklyChange":0,"side":"-"},{"timestamp":"1649908800","name":"SuDoResearch","profit":"127477304991","dailyChange":0,"weeklyChange":0,"side":"-"},{"timestamp":"1649908800","name":"Winter-Pink-Fang","profit":"112186373504","dailyChange":6490371,"weeklyChange":49426785,"side":"Long"},{"timestamp":"1649908800","name":"alamedaresearchltd@gmail.com","profit":"169670395643","dailyChange":0,"weeklyChange":0,"side":"-"},{"timestamp":"1649908800","name":"aoa","profit":"338455097018","dailyChange":-28871543,"weeklyChange":-893559714,"side":"Short"},{"timestamp":"1649908800","name":"ningxin","profit":"241654552971","dailyChange":0,"weeklyChange":0,"side":"-"},{"timestamp":"1649908800","name":"xorq","profit":"127811730513","dailyChange":0,"weeklyChange":0,"side":"-"}]}